ccg_nlpy/TestPipelineNLPy.py
ccg_nlpy/__init__.py
ccg_nlpy/__main__.py
ccg_nlpy/download.py
ccg_nlpy/local_pipeline.py
ccg_nlpy/pipeline_base.py
ccg_nlpy/pipeline_config.py
ccg_nlpy/remote_pipeline.py
ccg_nlpy/utils.py
ccg_nlpy/config/pipeline.cfg
ccg_nlpy/core/__init__.py
ccg_nlpy/core/predicate_argument_view.py
ccg_nlpy/core/text_annotation.py
ccg_nlpy/core/view.py
ccg_nlpy/core/visualize.py
ccg_nlpy/protobuf/TextAnnotation_pb2.py
ccg_nlpy/protobuf/__init__.py
ccg_nlpy/server/__init__.py
ccg_nlpy/server/manage.py
ccg_nlpy/server/model_wrapper_server.py
ccg_nlpy/server/model_wrapper_server_local_pipeline.py
ccg_nlpy/server/model_wrapper_server_remote_pipeline.py
ccg_nlpy/server/example/__init__.py
ccg_nlpy/server/example/dummy_model.py
ccg_nlpy/server/example/example_model_wrapper_server.py
ccg_nlpy/server/server/__init__.py
ccg_nlpy/server/server/settings.py
ccg_nlpy/server/server/urls.py
ccg_nlpy/server/server/views.py
ccg_nlpy/server/server/wsgi.py
ccg_nlpy-1.10.0.dist-info/METADATA
ccg_nlpy-1.10.0.dist-info/RECORD
ccg_nlpy-1.10.0.dist-info/WHEEL
ccg_nlpy-1.10.0.dist-info/top_level.txt
