Metadata-Version: 2.1
Name: ccg-nlpy
Version: 1.10.0
Summary: Light-weight NLP annotators
Home-page: https://github.com/IllinoisCogComp/ccg_nlpy
Author: Cognitive Computation Group
Author-email: mssammon@illinois.edu
License: Research and Academic Use License
Keywords: NLP,natural language processing
Platform: UNKNOWN
Classifier: Development Status :: 3 - Alpha
Classifier: Intended Audience :: Science/Research
Classifier: Operating System :: Microsoft :: Windows
Classifier: Operating System :: POSIX
Classifier: Operating System :: Unix
Classifier: Operating System :: MacOS
Classifier: Programming Language :: Python :: 2
Classifier: Programming Language :: Python :: 2.6
Classifier: Programming Language :: Python :: 2.7
Classifier: Programming Language :: Python :: 3
Classifier: Programming Language :: Python :: 3.4
Classifier: Programming Language :: Python :: 3.5
Classifier: Programming Language :: Python :: 3.6
Classifier: Topic :: Scientific/Engineering
Requires-Dist: configparser
Requires-Dist: Cython
Requires-Dist: pyjnius
Requires-Dist: protobuf
Requires-Dist: requests
Requires-Dist: six
